nwcicdsetup/Context.py
nwcicdsetup/NWServiceContext.py
nwcicdsetup/__init__.py
nwcicdsetup/__main__.py
nwcicdsetup/circleci.py
nwcicdsetup/circleciapiclient.py
nwcicdsetup/circlecibuild.py
nwcicdsetup/circlecicontext.py
nwcicdsetup/circlecijob.py
nwcicdsetup/circleciworkflowjob.py
nwcicdsetup/dotnetdependencyresolver.py
nwcicdsetup/generator.py
nwcicdsetup/githubapiclient.py
nwcicdsetup/githubchangeset.py
nwcicdsetup/nwservice.py
nwcicdsetup/validationschema.py
nwcicdsetup/validator.py
nwcicdsetup-2.3.0.dist-info/WHEEL
nwcicdsetup-2.3.0.dist-info/METADATA
nwcicdsetup-2.3.0.dist-info/RECORD
