Metadata-Version: 2.1
Name: nwcicdsetup
Version: 2.3.0
Summary: 
Author: nativewaves
Author-email: dev@nativewaves.com
Requires-Python: >=3.9,<4.0
Classifier: Programming Language :: Python :: 3
Classifier: Programming Language :: Python :: 3.9
Classifier: Programming Language :: Python :: 3.10
Classifier: Programming Language :: Python :: 3.11
Requires-Dist: PyYAML (>=5.4.1,<6.0.0)
Requires-Dist: aiohttp (==3.7.2)
Requires-Dist: asyncio (>=3.4.3,<4.0.0)
Requires-Dist: pylint (>=2.11.1,<3.0.0)
Requires-Dist: schema (>=0.7.4,<0.8.0)
